cli_template/__init__.py
cli_template/main.py
tristan_cli-0.1.5.dist-info/entry_points.txt
tristan_cli-0.1.5.dist-info/WHEEL
tristan_cli-0.1.5.dist-info/METADATA
tristan_cli-0.1.5.dist-info/RECORD
